metaqueue/__init__.py
metaqueue/broker/__init__.py
metaqueue/broker/basic.py
metaqueue/connectors/__init__.py
metaqueue/connectors/interface.py
metaqueue/connectors/local.py
metaqueue/engine/__init__.py
metaqueue/engine/meta.py
metaqueue/exception/__init__.py
metaqueue/exception/container.py
metaqueue/instruments/__init__.py
metaqueue/instruments/concurrent.py
metaqueue/queue/__init__.py
metaqueue/queue/basic.py
metaqueue/store/__init__.py
metaqueue/store/data.py
metaqueue/utilities/__init__.py
metaqueue/utilities/tools.py
metaqueue-0.1.1.dist-info/LICENSE
metaqueue-0.1.1.dist-info/WHEEL
metaqueue-0.1.1.dist-info/METADATA
metaqueue-0.1.1.dist-info/RECORD
