Metadata-Version: 2.1
Name: metaqueue
Version: 0.1.1
Summary: Metaqueue enables simple and efficient metadata collection
Home-page: https://github.com/RaphSku/Metaqueue
License: BSD-3-Clause
Keywords: metadata,collection,management,storing
Author: RaphSku
Author-email: rapsku.dev@gmail.com
Requires-Python: >=3.10,<4.0
Classifier: License :: OSI Approved :: BSD License
Classifier: Programming Language :: Python :: 3
Classifier: Programming Language :: Python :: 3.10
Requires-Dist: attrs (>=22.1.0,<23.0.0)
Requires-Dist: numpy (>=1.23.4,<2.0.0)
Requires-Dist: psycopg2 (>=2.9.3,<3.0.0)
Requires-Dist: python-dotenv (>=0.21.0,<0.22.0)
Project-URL: Repository, https://github.com/RaphSku/Metaqueue
